customVOC/__init__.py
customVOC/customVOC.py
customVOC-0.0.1.dist-info/LICENSE
customVOC-0.0.1.dist-info/METADATA
customVOC-0.0.1.dist-info/WHEEL
customVOC-0.0.1.dist-info/top_level.txt
customVOC-0.0.1.dist-info/RECORD
