Metadata-Version: 2.1
Name: customVOC
Version: 0.0.1
Summary: Custom Pascal VOC Dataset reader for PyTorch
Home-page: https://github.com/aljbri/customPascalVOC
Author: Aljbri Abdussalam
Author-email: Aljbri Abdussalam <mr.aljbri@gmail.com>
Project-URL: home-page, https://github.com/aljbri/customPascalVOC
Project-URL: issues, https://github.com/aljbri/customPascalVOC/issues
Keywords: Pascal VOC,VOC,Dataset loader,Dataset reader
Classifier: Programming Language :: Python :: 3
Classifier: License :: OSI Approved :: MIT License
Classifier: Operating System :: OS Independent
Requires-Python: >=3.6
License-File: LICENSE
Requires-Dist: torchvision
